netbox_manager/__init__.py
netbox_manager/dtl.py
netbox_manager/main.py
netbox_manager/requirements.yml
netbox_manager/settings.toml.sample
netbox_manager-0.20260129.0.dist-info/licenses/LICENSE
netbox_manager-0.20260129.0.dist-info/METADATA
netbox_manager-0.20260129.0.dist-info/WHEEL
netbox_manager-0.20260129.0.dist-info/entry_points.txt
netbox_manager-0.20260129.0.dist-info/top_level.txt
netbox_manager-0.20260129.0.dist-info/RECORD
