Metadata-Version: 2.4
Name: netbox-manager
Version: 0.20260129.0
Summary: NetBox manager
Author-email: OSISM community <info@osism.tech>
License:                                  Apache License
Project-URL: Homepage, https://github.com/osism/netbox-manager
Project-URL: Bug Tracker, https://github.com/osism/netbox-manager/issues
Classifier: Development Status :: 5 - Production/Stable
Classifier: Environment :: Console
Classifier: Intended Audience :: Information Technology
Classifier: License :: OSI Approved :: Apache Software License
Classifier: Operating System :: OS Independent
Classifier: Programming Language :: Python
Classifier: Programming Language :: Python :: 3 :: Only
Classifier: Programming Language :: Python :: 3
Classifier: Programming Language :: Python :: 3.8
Classifier: Programming Language :: Python :: 3.9
Classifier: Programming Language :: Python :: 3.10
Classifier: Programming Language :: Python :: 3.11
Classifier: Programming Language :: Python :: 3.12
Classifier: Programming Language :: Python :: 3.13
Classifier: Programming Language :: Python :: 3.14
Requires-Python: >=3.8
License-File: LICENSE
Requires-Dist: GitPython==3.1.46
Requires-Dist: Jinja2==3.1.6
Requires-Dist: PyYAML==6.0.3
Requires-Dist: ansible-core==2.19.3
Requires-Dist: ansible-runner==2.4.2
Requires-Dist: dynaconf==3.2.12
Requires-Dist: loguru==0.7.3
Requires-Dist: pynetbox==7.6.1
Requires-Dist: setuptools==80.10.2
Requires-Dist: sushy==5.9.0
Requires-Dist: typer==0.21.1
Requires-Dist: yamale==6.1.0
Dynamic: license-file
